[{"model": "memberships.membership", "pk": 1, "fields": {"slug": "free", "membership_type": "Free", "price": 0, "stripe_plan_id": "price_1H8lvuJVYSpLhqQufQe4bExh"}}, {"model": "memberships.membership", "pk": 2, "fields": {"slug": "pro", "membership_type": "Professional", "price": 20, "stripe_plan_id": "price_1H5ofGJVYSpLhqQu8BjTG1Qu"}}, {"model": "memberships.usermembership", "pk": 2, "fields": {"user": 2, "stripe_customer_id": "ssfsfdsfsfsf", "membership": 2}}, {"model": "memberships.usermembership", "pk": 7, "fields": {"user": 8, "stripe_customer_id": "cus_HrbxD2B0QyT34F", "membership": 2}}, {"model": "memberships.usermembership", "pk": 9, "fields": {"user": 10, "stripe_customer_id": "cus_HxtlyuDufpX8Ei", "membership": 2}}, {"model": "memberships.usermembership", "pk": 10, "fields": {"user": 11, "stripe_customer_id": "cus_Hy2mpvxmzuyC0i", "membership": 1}}, {"model": "memberships.usermembership", "pk": 11, "fields": {"user": 12, "stripe_customer_id": "cus_Hy2sL4KO7WXQb1", "membership": 2}}, {"model": "memberships.usermembership", "pk": 12, "fields": {"user": 13, "stripe_customer_id": "cus_Hz1iPY0yZ07t1o", "membership": 2}}, {"model": "memberships.usermembership", "pk": 13, "fields": {"user": 14, "stripe_customer_id": "cus_I1X5FfVsQPzQwV", "membership": 1}}, {"model": "memberships.usermembership", "pk": 14, "fields": {"user": 15, "stripe_customer_id": "cus_I1YSg7sCxjHINl", "membership": 1}}, {"model": "memberships.subscription", "pk": 3, "fields": {"user_membership": 7, "stripe_subscription_id": "sub_I3zKAl2GtW6VnH", "active": true}}]